moreloops/__init__.py
moreloops-0.0.1.dist-info/LICENSE
moreloops-0.0.1.dist-info/METADATA
moreloops-0.0.1.dist-info/WHEEL
moreloops-0.0.1.dist-info/top_level.txt
moreloops-0.0.1.dist-info/RECORD
