Metadata-Version: 2.1
Name: moreloops
Version: 0.0.1
Summary: Allows one to use tons of loops not natively supported in python
Home-page: https://www.beyonce.com
Author: hunterg
Author-email: redissuslolol@gmail.com
License: UNKNOWN
Platform: UNKNOWN
Classifier: Programming Language :: Python :: 3
Classifier: License :: OSI Approved :: MIT License
Classifier: Operating System :: OS Independent
Requires-Python: >=3.6
Requires-Dist: decorate-all-methods
Requires-Dist: docifyPLUS
